pyku/__init__.py
pyku/cli.py
pyku/pyku.py
pyku-0.0.0.dist-info/METADATA
pyku-0.0.0.dist-info/RECORD
pyku-0.0.0.dist-info/WHEEL
pyku-0.0.0.dist-info/entry_points.txt
pyku-0.0.0.dist-info/top_level.txt
