Metadata-Version: 2.1
Name: pyku
Version: 0.0.0
Summary: Turn sentences into haiku.
Home-page: https://github.com/sethwoodworth/pyku
Author: Seth Wolfwood
Author-email: seth@sethish.com
License: GNU General Public License v3
Keywords: pyku
Platform: UNKNOWN
Classifier: Development Status :: 2 - Pre-Alpha
Classifier: Intended Audience :: Developers
Classifier: License :: OSI Approved :: GNU General Public License v3 (GPLv3)
Classifier: Natural Language :: English
Classifier: Programming Language :: Python :: 3.6
Requires-Dist: Click (>=6.0)
